{
  "legacy.container.tab.building_blocks": {
    "icon": "legacy:icon/structures",
    "listing": [
      "minecraft:stone", "minecraft:grass_block", "minecraft:dirt", "minecraft:cobblestone", "minecraft:sand", "minecraft:sandstone", "minecraft:gold_block", "minecraft:iron_block", "minecraft:lapis_block", "minecraft:diamond_block", "minecraft:coal_ore", "minecraft:lapis_ore", "minecraft:diamond_ore", "minecraft:redstone_ore", "minecraft:iron_ore", "minecraft:gold_ore", "minecraft:smooth_stone_slab", "minecraft:sandstone_slab", "minecraft:oak_slab", "minecraft:cobblestone_slab", "minecraft:bedrock", "minecraft:oak_planks", "minecraft:oak_log", "minecraft:spruce_log", "minecraft:birch_log", "minecraft:gravel", "minecraft:bricks", "minecraft:mossy_cobblestone", "minecraft:obsidian", "minecraft:clay", "minecraft:ice", "minecraft:snow_block", "minecraft:netherrack", "minecraft:soul_sand", "minecraft:glowstone"
    ]
  },
  "legacy.container.tab.decoration": {
    "icon": "legacy:icon/decoration",
    "listing": [
      "minecraft:sponge", "minecraft:wet_sponge", "minecraft:carved_pumpkin", "minecraft:jack_o_lantern", "minecraft:oak_sapling", "minecraft:spruce_sapling", "minecraft:birch_sapling", "minecraft:oak_leaves", "minecraft:spruce_leaves", "minecraft:birch_leaves", "minecraft:torch", "minecraft:short_grass", "minecraft:fern", "minecraft:dead_bush", "minecraft:dandelion", "minecraft:poppy", "minecraft:brown_mushroom", "minecraft:red_mushroom", "minecraft:cactus", "minecraft:snow", "minecraft:glass", "minecraft:painting", "minecraft:oak_sign", "minecraft:bookshelf", "minecraft:red_wool", "minecraft:orange_wool", "minecraft:yellow_wool", "minecraft:lime_wool", "minecraft:light_blue_wool", "minecraft:cyan_wool", "minecraft:blue_wool",  "minecraft:purple_wool", "minecraft:magenta_wool", "minecraft:pink_wool", "minecraft:white_wool", "minecraft:light_gray_wool", "minecraft:gray_wool", "minecraft:black_wool", "minecraft:green_wool", "minecraft:brown_wool"
    ]
  },
  "legacy.container.tab.redstone_and_transport": {
    "icon": "legacy:icon/redstone_and_transport",
    "listing": [
      "minecraft:dispenser", "minecraft:note_block", "minecraft:tnt", "minecraft:lever", "minecraft:stone_button", "minecraft:stone_pressure_plate", "minecraft:oak_pressure_plate", "minecraft:redstone", "minecraft:redstone_torch", "minecraft:repeater", "minecraft:rail", "minecraft:powered_rail", "minecraft:detector_rail", "minecraft:minecart", "minecraft:chest_minecart", "minecraft:furnace_minecart", "minecraft:saddle", "minecraft:oak_boat", "minecraft:oak_stairs", "minecraft:cobblestone_stairs", "minecraft:ladder", "minecraft:oak_trapdoor", "minecraft:oak_door", "minecraft:iron_door"
    ]
  },
  "legacy.container.tab.materials": { 
    "icon": "legacy:icon/materials",
    "listing": [
      "minecraft:coal", "minecraft:charcoal", "minecraft:diamond", "minecraft:iron_ingot", "minecraft:gold_ingot", "minecraft:brick", "minecraft:stick", "minecraft:bowl", "minecraft:string", "minecraft:feather", "minecraft:flint", "minecraft:leather", "minecraft:gunpowder", "minecraft:clay_ball", "minecraft:glowstone_dust", "minecraft:wheat_seeds", "minecraft:wheat", "minecraft:sugar_cane", "minecraft:egg", "minecraft:sugar", "minecraft:red_dye", "minecraft:orange_dye", "minecraft:yellow_dye", "minecraft:lime_dye", "minecraft:light_blue_dye", "minecraft:cyan_dye", "minecraft:lapis_lazuli", "minecraft:purple_dye", "minecraft:magenta_dye", "minecraft:pink_dye", "minecraft:bone_meal", "minecraft:light_gray_dye", "minecraft:gray_dye", "minecraft:ink_sac", "minecraft:green_dye", "minecraft:cocoa_beans"
    ]
  },
  "legacy.container.tab.food": {
    "icon": "legacy:icon/food",
    "listing": [
      "minecraft:apple", "minecraft:golden_apple", "minecraft:mushroom_stew", "minecraft:bread", "minecraft:cake", "minecraft:cookie", "minecraft:cooked_cod", "minecraft:cod", "minecraft:cooked_porkchop", "minecraft:porkchop"
    ]
  },
  "legacy.container.tab.tools_and_armour": {
    "icon": "legacy:icon/tools",
    "listing": [
      "minecraft:compass", "minecraft:leather_helmet", "minecraft:leather_chestplate", "minecraft:leather_leggings", "minecraft:leather_boots", "minecraft:wooden_sword", "minecraft:wooden_shovel", "minecraft:wooden_pickaxe", "minecraft:wooden_axe", "minecraft:wooden_hoe", "minecraft:map", "minecraft:chainmail_helmet", "minecraft:chainmail_chestplate", "minecraft:chainmail_leggings", "minecraft:chainmail_boots", "minecraft:stone_sword", "minecraft:stone_shovel", "minecraft:stone_pickaxe", "minecraft:stone_axe", "minecraft:stone_hoe", "minecraft:bow", "minecraft:iron_helmet", "minecraft:iron_chestplate", "minecraft:iron_leggings", "minecraft:iron_boots", "minecraft:iron_sword", "minecraft:iron_shovel", "minecraft:iron_pickaxe", "minecraft:iron_axe", "minecraft:iron_hoe", "minecraft:arrow", "minecraft:golden_helmet", "minecraft:golden_chestplate", "minecraft:golden_leggings", "minecraft:golden_boots", "minecraft:golden_sword", "minecraft:golden_shovel", "minecraft:golden_pickaxe", "minecraft:golden_axe", "minecraft:golden_hoe", "minecraft:flint_and_steel", "minecraft:diamond_helmet", "minecraft:diamond_chestplate", "minecraft:diamond_leggings", "minecraft:diamond_boots", "minecraft:diamond_sword", "minecraft:diamond_shovel", "minecraft:diamond_pickaxe", "minecraft:diamond_axe", "minecraft:diamond_hoe", "minecraft:clock", "minecraft:fishing_rod"
    ]
  },
  "legacy.container.tab.egg": {
    "icon": "legacy:icon/egg",
    "listing": [
      "minecraft:creeper_spawn_egg", "minecraft:skeleton_spawn_egg", "minecraft:spider_spawn_egg", "minecraft:zombie_spawn_egg", "minecraft:slime_spawn_egg", "minecraft:ghast_spawn_egg", "minecraft:zombified_piglin_spawn_egg", "minecraft:pig_spawn_egg", "minecraft:sheep_spawn_egg", "minecraft:cow_spawn_egg", "minecraft:chicken_spawn_egg", "minecraft:wolf_spawn_egg"
    ]
  },
  "legacy.container.tab.misc": { 
    "icon": "legacy:icon/misc",
    "listing": [
      "minecraft:chest", "minecraft:crafting_table", "minecraft:furnace", "minecraft:jukebox", "minecraft:oak_fence", "minecraft:red_bed", "minecraft:bucket", "minecraft:lava_bucket", "minecraft:water_bucket", "minecraft:milk_bucket", "minecraft:snowball", "minecraft:paper", "minecraft:book", "minecraft:slime_ball", "minecraft:bone", "minecraft:spawner", "minecraft:music_disc_13", "minecraft:music_disc_cat"
    ]
  }
}